{
    "collectionName": "components_shared_badges",
    "info": {
        "displayName": "badge",
        "icon": "grid"
    },
    "options": {},
    "attributes": {
        "name": {
            "type": "string"
        },
        "sort": {
            "type": "integer"
        },
        "label": {
            "type": "string"
        },
        "badge_id": {
            "type": "string"
        },
        "class": {
            "type": "text"
        },
        "css": {
            "type": "customField",
            "customField": "plugin::strapi-code-editor-custom-field.code-editor-text",
            "options": {
                "language": "css"
            }
        }
    },
    "config": {}
}
